simulata/__init__.py
simulata/simulata.py
simulata/test.py
simulata-0.0.8.dist-info/DESCRIPTION.rst
simulata-0.0.8.dist-info/METADATA
simulata-0.0.8.dist-info/RECORD
simulata-0.0.8.dist-info/WHEEL
simulata-0.0.8.dist-info/metadata.json
simulata-0.0.8.dist-info/top_level.txt
