Metadata-Version: 2.0
Name: simulata
Version: 0.0.8
Summary: Creating simulated datasets
Home-page: http://github.com/staeiou/simulata
Author: Stuart Geiger
Author-email: stuart@stuartgeiger.com
License: MIT
Platform: UNKNOWN
Requires-Dist: numpy
Requires-Dist: pandas
